mongodb_connect/__init__.py
mongodb_connect/mongo_crud.py
Monogodb_Connect_automation-0.0.4.dist-info/METADATA
Monogodb_Connect_automation-0.0.4.dist-info/WHEEL
Monogodb_Connect_automation-0.0.4.dist-info/top_level.txt
Monogodb_Connect_automation-0.0.4.dist-info/RECORD
